Workbook

Sheet EDO. SIT. FINAC.
B3: PAGOS ENTRENADORES | F3: INGRESOS MES | J3: GASTOS FIJOS | N3: GASTOS VARIABLES | R3: DINERO EN CAJA
C4: ERICK | D4: JUAN | F4: CAJA FEBRERO | H4: 1590 | J4: CANCHA | L4: =PAGOS!G38+PAGOS!L38+PAGOS!Q38+PAGOS!V38 -> 1600 | N4: INSCRICPCIÓN LIGA | O4: 1000 | P4: 45751 | R4: EN BANCOS | T4: 0
B5: ENERO | C5: 5617 | D5: 5617 | F5: PAGOS ATRASADOS | H5: =ATRASOS!E40 -> 3570 | J5: ARBITRAJE | L5: =PAGOS!G39+PAGOS!L39+PAGOS!Q39+PAGOS!V39 -> 1500 | R5: EFECTIVO | T5: 0 | U5: 45748
B6: FEBRERO | C6: 4545 | D6: 4545 | F6: COLEGIATURA | H6: =PAGOS!G37+PAGOS!L37+PAGOS!Q37+PAGOS!V37 -> 2535 | R6: TOTAL | T6: =SUM(T4:T5) -> 0
B7: MARZO | C7: 3500 | D7: 3500 | F7: ARBITRAJE | H7: =PAGOS!H37+PAGOS!M37+PAGOS!R37+PAGOS!W37 -> 2240
C8: 0 | D8: 0
C9: 0 | D9: 0
C10: 0 | D10: 0
C11: 0 | D11: 0
F12: TOTAL | H12: =SUM(H4:H10) -> 9935 | J12: TOTAL | L12: =SUM(L4:L7) -> 3100 | N12: TOTAL | O12: =SUM(O4:O11) -> 1000
C13: =SUM(C5:C12) -> 13662 | D13: =SUM(D5:D12) -> 13662
B14: TOTAL | C14: =C13+D13 -> 27324
B19: UTILIDAD | J19: POR REPARTIR ENTRE PROFESORES | N19: =F23 -> 5835
B20: INGRESOS | F20: =H12 -> 9935 | J20: PARA CADA UNO | N20: =N19/2 -> 2917.5
B21: GASTOS FIJOS Y VARIABLES | F21: =L12+O12 -> 4100
F23: =F20-F21 -> 5835

Sheet PAGOS
D2: ABRIL
D3: SEMANA 1 | I3: SEMANA 2 | N3: SEMANA 3 | S3: SEMANA 4
B4: NO. | C4: NOMBRE | D4: MAR | E4: VIE | F4: SÁB | G4: COLEGIATURA | H4: ARBITRAJE | I4: MAR | J4: VIE | K4: SÁB | L4: COLEGIATURA | M4: ARBITRAJE | N4: MAR | O4: VIE | P4: SÁB | Q4: COLEGIATURA | R4: ARBITRAJE | S4: MAR | T4: VIE | U4: SÁB | V4: COLEGIATURA | W4: ARBITRAJE
D5: 1 | E5: 4 | F5: 5 | I5: 8 | J5: 11 | K5: 12 | N5: 15 | O5: 18 | P5: 19 | S5: 22 | T5: 25 | U5: 26
B6: 1 | C6: Alejandro | D6: PAGADO | G6: 0 | H6: 0 | I6: PAGADO | L6: 0 | M6: 0 | N6: PAGADO | Q6: 0 | R6: 0 | S6: PAGADO | V6: 0 | W6: 0
B7: 2 | C7: Briand | D7: PENDIENTE | G7: 0 | H7: 0 | I7: PENDIENTE | L7: 0 | M7: 0 | N7: PENDIENTE | Q7: 0 | R7: 0 | S7: PENDIENTE | V7: 0 | W7: 0
B8: 3 | C8: Carlos | D8: PAGADO | G8: 130 | H8: 70 | I8: PAGADO | L8: 130 | M8: 70 | N8: PENDIENTE | Q8: 0 | R8: 0 | S8: PENDIENTE | V8: 0 | W8: 0
B9: 4 | C9: Cristopher | D9: PENDIENTE | G9: 0 | H9: 0 | I9: PENDIENTE | L9: 0 | M9: 70 | N9: PENDIENTE | Q9: 0 | R9: 0 | S9: PENDIENTE | V9: 0 | W9: 0
B10: 5 | C10: Derek | D10: PAGADO | G10: 130 | H10: 70 | I10: PAGADO | L10: 130 | M10: 70 | N10: PENDIENTE | Q10: 0 | R10: 0 | S10: PENDIENTE | V10: 0 | W10: 0
B11: 6 | C11: Diego | D11: PENDIENTE | G11: 130 | H11: 70 | I11: PAGADO | L11: 130 | M11: 70 | N11: PENDIENTE | Q11: 0 | R11: 0 | S11: PENDIENTE | V11: 0 | W11: 0
B12: 7 | C12: Emiliano | D12: PENDIENTE | G12: 0 | H12: 70 | I12: PENDIENTE | L12: 0 | M12: 70 | N12: PENDIENTE | Q12: 0 | R12: 0 | S12: PENDIENTE | V12: 0 | W12: 0
B13: 8 | C13: Emmanuel | D13: PENDIENTE | G13: 0 | H13: 70 | I13: PENDIENTE | L13: 0 | M13: 0 | N13: PENDIENTE | Q13: 0 | R13: 0 | S13: PENDIENTE | V13: 0 | W13: 0
B14: 9 | C14: Esteban | D14: PAGADO | G14: 130 | H14: 0 | I14: PENDIENTE | L14: 130 | M14: 0 | N14: PENDIENTE | Q14: 0 | R14: 0 | S14: PENDIENTE | V14: 0 | W14: 0
B15: 10 | C15: Franco | D15: PAGADO | G15: 0 | H15: 0 | I15: PAGADO | L15: 0 | M15: 0 | N15: PENDIENTE | Q15: 0 | R15: 0 | S15: PENDIENTE | V15: 0 | W15: 0
B16: 11 | C16: Jafet | D16: PAGADO | G16: 130 | H16: 70 | I16: PENDIENTE | L16: 0 | M16: 0 | N16: PENDIENTE | Q16: 0 | R16: 0 | S16: PENDIENTE | V16: 0 | W16: 0
B17: 12 | C17: José | D17: PENDIENTE | G17: 0 | H17: 0 | I17: PENDIENTE | L17: 0 | M17: 0 | N17: PENDIENTE | Q17: 0 | R17: 0 | S17: PENDIENTE | V17: 0 | W17: 0
... B33: 28 | C33: Ximena | D33: PENDIENTE | G33: 0 | H33: 70 | I33: PENDIENTE | L33: 0 | M33: 0 | N33: PENDIENTE | Q33: 0 | R33: 0 | S33: PENDIENTE | V33: 0 | W33: 0
G37: =SUM(G6:G33) -> 1365 | H37: =SUM(H6:H33) -> 1260 | L37: =SUM(L6:L33) -> 1170 | M37: =SUM(M6:M33) -> 980 | Q37: =SUM(Q6:Q33) -> 0 | R37: =SUM(R6:R33) -> 0 | V37: =SUM(V6:V33) -> 0 | W37: =SUM(W6:W33) -> 0
D38: CANCHA | E38: CANCHA | G38: 800 | I38: CANCHA | J38: CANCHA | L38: 800 | N38: CANCHA | O38: CANCHA | Q38: 0 | S38: CANCHA | T38: CANCHA | V38: 0
D39: ARBITRAJE | E39: ARBITRAJE | G39: 750 | I39: ARBITRAJE | J39: ARBITRAJE | L39: 750 | N39: ARBITRAJE | O39: ARBITRAJE | Q39: 0 | S39: ARBITRAJE | T39: ARBITRAJE | V39: 0

Sheet ATRASOS
D2: MARZO | X2: PENDIENTES
D3: SEMANA 1 | I3: SEMANA 2 | N3: SEMANA 3 | S3: SEMANA 4
B4: NO. | C4: NOMBRE | D4: MAR | E4: VIE | F4: SÁB | G4: COLEGIATURA | H4: ARBITRAJE | I4: MAR | J4: VIE | K4: SÁB | L4: COLEGIATURA | M4: ARBITRAJE | N4: MAR | O4: VIE | P4: SÁB | Q4: COLEGIATURA | R4: ARBITRAJE | S4: MAR | T4: VIE | U4: SÁB | V4: COLEGIATURA | W4: ARBITRAJE | X4: COLEGIATURAS ENERO | Y4: TOTAL $ | Z4: COLEGIATURAS FEBRERO | AA4: TOTAL $ | AB4: ARBITRAJES FEBRERO | AC4: TOTAL $ | AD4: COLEGIATURAS MARZO | AE4: TOTAL $ | AF4: ARBITRAJES MARZO | AG4: TOTAL $ | AH4: INSCRIPCIÓN | AI4: GRAN TOTAL
D5: 4 | E5: 7 | F5: 8 | I5: 11 | J5: 14 | K5: 15 | N5: 18 | O5: 21 | P5: 22 | S5: 25 | T5: 28 | U5: 29
B6: 2 | C6: Briand | D6: PAGADO | G6: 130 | H6: 0 | I6: PENDIENTE | L6: 0 | M6: 70 | N6: PENDIENTE | Q6: 0 | R6: 0 | S6: PENDIENTE | V6: 0 | W6: 0 | X6: NA | Y6: 0 | AA6: 200 | AB6: 0 | AC6: 0 | AD6: SEM 2 - 3 | AE6: 260 | AH6: 0 | AI6: =Y6+AA6+AC6+AE6+AH6 -> 460
B7: 4 | C7: Cristopher | D7: PENDIENTE | G7: 0 | H7: 0 | I7: PENDIENTE | L7: 0 | M7: 70 | N7: PENDIENTE | Q7: 0 | R7: 70 | S7: PENDIENTE | W7: 70 | X7: NA | Y7: 0 | AA7: 2350 | AD7: SEM 1 - 4 | AE7: 520 | AH7: 0 | AI7: =Y7+AA7+AC7+AE7+AH7 -> 2870
B8: 7 | C8: Emiliano | D8: PAGADO | G8: 130 | H8: 0 | I8: PAGADO | L8: 130 | M8: 0 | N8: PAGADO | Q8: 130 | R8: 70 | S8: PENDIENTE | X8: NA | Y8: 0 | Z8: NA | AA8: 0 | AB8: NA | AC8: 0 | AD8: SEM 4 | AE8: 130 | AF8: NA | AG8: 0 | AH8: 0 | AI8: =Y8+AA8+AC8+AE8+AH8 -> 130
B9: 8 | C9: Emmanuel | D9: PAGADO | G9: 130 | H9: 0 | I9: PAGADO | L9: 130 | M9: 0 | N9: PAGADO | Q9: 130 | R9: 70 | S9: PAGADO | V9: 130 | W9: 0 | X9: SEM 2 - 4 ENE | Y9: 390 | Z9: SEM 1 - 4 | AA9: 520 | AB9: SEM 3 FEB | AC9: 70 | AD9: SEM 1 - 4 | AE9: 520 | AF9: NA | AG9: 0 | AH9: 0 | AI9: =Y9+AA9+AC9+AE9+AH9 -> 1500 | AJ9: PAGADO
B10: 12 | C10: José | D10: PAGADO | G10: 130 | H10: 0 | I10: PAGADO | L10: 130 | M10: 0 | N10: PAGADO | Q10: 130 | R10: 0 | S10: PAGADO | V10: 130 | W10: 0 | X10: SEM 4 ENE | Y10: 130 | Z10: SEM 1 - 2 FEB | AA10: 260 | AB10: NA | AC10: 0 | AD10: SEM 1 Y 4 | AE10: 260 | AF10: NA | AG10: 0 | AH10: 0 | AI10: =Y10+AA10+AC10+AE10+AH10 -> 650 | AJ10: PAGADO
B11: 14 | C11: Leo | D11: PENDIENTE | G11: 0 | H11: 70 | I11: PENDIENTE | L11: 0 | M11: 0 | N11: PENDIENTE | Q11: 0 | R11: 0 | S11: PENDIENTE | W11: 70 | X11: NA | Y11: 0 | Z11: NA | AA11: 0 | AB11: NA | AC11: 0 | AD11: SEM 1 - 4 | AE11: 520 | AF11: NA | AG11: 0 | AH11: 730 | AI11: =Y11+AA11+AC11+AE11+AH11 -> 1250
B12: 15 | C12: Liam | D12: PENDIENTE | G12: 130 | H12: 0 | I12: PENDIENTE | L12: 130 | M12: 0 | N12: PENDIENTE | Q12: 130 | R12: 0 | S12: PENDIENTE | V12: 130 | W12: 70 | X12: NA | Y12: 0 | Z12: NA | AA12: 0 | AB12: SEM 4 | AC12: 70 | AD12: SEM 1 - 4 | AE12: 520 | AF12: NA | AG12: 0 | AH12: 300 | AI12: =Y12+AA12+AC12+AE12+AH12 -> 890
B13: 17 | C13: Mathías | D13: PENDIENTE | G13: 0 | H13: 70 | I13: PENDIENTE | L13: 0 | M13: 70 | N13: PENDIENTE | Q13: 0 | R13: 70 | S13: PENDIENTE | W13: 70 | X13: NA | Y13: 0 | Z13: NA | AA13: 0 | AB13: NA | AC13: 0 | AD13: NA | AE13: 0 | AF13: NA | AG13: 0 | AH13: 0 | AI13: =Y13+AA13+AC13+AE13+AH13 -> 0
B14: 20 | C14: Ricardo | D14: PAGADO | G14: 130 | H14: 0 | I14: PENDIENTE | L14: 0 | M14: 70 | N14: PAGADO | Q14: 130 | R14: 70 | S14: PENDIENTE | X14: SEM 3 - 4 | Y14: 200 | Z14: NA | AA14: 0 | AB14: NA | AC14: 0 | AD14: SEM 3 | AE14: 130 | AF14: NA | AG14: 0 | AH14: 0 | AI14: =Y14+AA14+AC14+AE14+AH14 -> 330
B15: 23 | C15: Santiago Uriel | D15: PAGADO | G15: 65 | H15: 70 | I15: PAGADO | L15: 65 | M15: 0 | N15: PENDIENTE | Q15: 0 | R15: 70 | S15: PENDIENTE | W15: 70 | X15: NA | Y15: 0 | Z15: NA | AA15: 0 | AB15: NA | AC15: 0 | AD15: SEM 3 - 4 | AE15: 130 | AF15: NA | AG15: 0 | AH15: 500 | AI15: =Y15+AA15+AC15+AE15+AH15 -> 630
B16: 25 | C16: Yael | D16: PAGADO | G16: 130 | H16: 70 | I16: PAGADO | L16: 130 | M16: 0 | N16: PAGADO | Q16: 130 | R16: 70 | S16: PAGADO | V16: 130 | W16: 70 | X16: NA | Y16: 0 | Z16: NA | AA16: 0 | AB16: NA | AC16: 0 | AD16: SEM 4 | AE16: 130 | AF16: SEM 4 | AG16: 70 | AH16: 0 | AI16: =Y16+AA16+AC16+AE16+AG16 -> 200 | AJ16: PAGADO
B17: 26 | C17: Ximena | D17: PENDIENTE | G17: 0 | H17: 70 | I17: PENDIENTE | L17: 0 | M17: 70 | N17: PENDIENTE | Q17: 0 | R17: 70 | S17: PENDIENTE | X17: NA | Y17: 0 | AI17: 2500 | AJ17: SOLO LE ESTAMOS COBRANDO ENERO-MAR E INSCRIPCIÓN
C20: DESCRIPCIÓN | D20: FECHA | E20: MONTO
C21: PAGO JOSE DELFINO | D21: 45747 | E21: 650
C22: PAGO YAEL | D22: 45748 | E22: 200
C23: PAGO LIAM | D23: 45748 | E23: 520
C24: PAGO CRIS - MATHIAS | D24: 45751 | E24: 700
C25: PAGO EMMANUEL | D25: 45751 | E25: 1500
E26: 0
E27: 0
E28: 0
E29: 0
E30: 0
E31: 0
E32: 0
E33: 0
E34: 0
E35: 0
E36: 0
E37: 0
... E39: 0
C40: TOTAL ABRIL | E40: =SUM(E21:E39) -> 3570

Sheet CALENDARIO
B2: CALENDARIO
B4: SEPTIEMBRE
B5: VIE | C5: SÁB | D5: MAR | E5: VIE | F5: SÁB
B6: 20 | C6: 21 | D6: 24 | E6: 27 | F6: 28
B7: OCTUBRE
B8: MAR | C8: VIE | D8: SÁB | E8: MAR | F8: VIE | G8: SÁB | H8: MAR | I8: VIE | J8: SÁB | K8: MAR | L8: VIE | M8: SÁB
B9: 1 | C9: 4 | D9: 5 | E9: 8 | F9: 11 | G9: 12 | H9: 15 | I9: 18 | J9: 19 | K9: 22 | L9: 25 | M9: 26
B10: ENTRENAMIENTOS | D10: PRÁCTICA | E10: ENTRENAMIENTOS | G10: JORNADA 1 | H10: ENTRENAMIENTOS | J10: JORNADA 2 | K10: ENTRENAMIENTOS | M10: JORNADA 3
B11: NOVIEMBRE
B12: MAR | C12: VIE | D12: SÁB | E12: MAR | F12: VIE | G12: SÁB | H12: MAR | I12: VIE | J12: SÁB | K12: MAR | L12: VIE | M12: SÁB | N12: MAR | O12: VIE | P12: SÁB
B13: 29 | C13: 1 | D13: 2 | E13: 5 | F13: 8 | G13: 9 | H13: 12 | I13: 15 | J13: 16 | K13: 19 | L13: 22 | M13: 23 | N13: 26 | O13: 29 | P13: 30
B14: ENTRENAMIENTOS | D14: JORNADA 4 | E14: ENTRENAMIENTOS | G14: JORNADA 5 | H14: ENTRENAMIENTOS | J14: JORNADA 6 | K14: ENTRENAMIENTOS | M14: JORNADA 7 | N14: ENTRENAMIENTOS | P14: JORNADA 8
B15: DICIEMBRE
B16: MAR | C16: VIE | D16: SÁB | E16: MAR | F16: VIE | G16: SÁB | H16: MAR | I16: VIE | J16: SÁB | K16: MAR | L16: VIE | M16: SÁB | N16: MAR | O16: VIE | P16: SÁB
B17: 3 | C17: 6 | D17: 7 | E17: 10 | F17: 13 | G17: 14 | H17: 17 | I17: 20 | J17: 21 | K17: 24 | L17: 27 | M17: 28 | N17: 31 | O17: 3 | P17: 4
B18: ENTRENAMIENTOS | D18: JORNADA 9 | E18: ENTRENAMIENTOS | G18: JORNADA 10 | H18: ENTRENAMIENTOS | J18: NA | K18: VACACIONES
B19: ENERO
B20: MAR | C20: VIE | D20: SÁB | E20: MAR | F20: VIE | G20: SÁB | H20: MAR | I20: VIE | J20: SÁB | K20: MAR | L20: VIE | M20: SÁB
B21: 7 | C21: 10 | D21: 11 | E21: 14 | F21: 17 | G21: 18 | H21: 21 | I21: 24 | J21: 25 | K21: 28 | L21: 31 | M21: 1
B22: ENTRENAMIENTOS | D22: PRÁCTICA | E22: ENTRENAMIENTOS | G22: JORNADA 11 | H22: ENTRENAMIENTOS | J22: JORNADA 12 | K22: ENTRENAMIENTOS | M22: SUSPENDIDA
B23: FEBRERO
B24: MAR | C24: VIE | D24: SÁB | E24: MAR | F24: VIE | G24: SÁB | H24: MAR | I24: VIE | J24: SÁB
B25: 4 | C25: 7 | D25: 8 | E25: 11 | F25: 14 | G25: 15 | H25: 18 | I25: 21 | J25: 22
B26: ENTRENAMIENTOS | D26: JORNADA 13 | E26: ENTRENAMIENTOS | H26: ENTRENAMIENTOS | J26: JORNADA 13
B28: OBSERVACIONES
B29: JORNADA 4 | C29: Se pospusó, se jugará el 18-nov

Sheet PAGO ARBITRAJE
B2: JORNADA | C2: CATEGORÍA | D2: CAMPO | E2: RIVAL | F2: FECHA | G2: MONTO | H2: POR PAGAR | I2: =SUM(G3:G5) -> 690 | J2: ESTE DINERO LO DEBO PAGAR YO
B3: 3ER LUGAR | C3: SUB 9 | D3: CAR | E3: PANTERAS | F3: 45359 | G3: 230
B4: PRÁCTICA | C4: PONY | D4: CAR | E4: TRIANGULAR | F4: 45366 | G4: 230
B5: PRÁCTICA | C5: SUB 11 | D5: CAR | E5: TREBOL | F5: 45366 | G5: 230
B6: JORNADA 1 | C6: PONY | D6: CAR | E6: MANCHESTER CITY ACOZAC | F6: 45373 | G6: 230 | H6: PAGADO
B7: JORNADA 1 | C7: SUB 9 | D7: CAR | E7: MACROSOCCER | F7: 45373 | G7: 230 | H7: PAGADO
B8: JORNADA 1 | C8: SUB 11 | D8: CAR | E8: TREBOL | F8: 45373 | G8: 230 | H8: PAGADO
B9: JORNADA 2 | C9: PONY | D9: CAR | E9: ATLANTE | F9: 45380 | G9: 230 | H9: PENDIENTE
B10: JORNADA 2 | C10: SUB 9 | D10: TLAPACOYA | E10: GUERREROS | F10: 45380 | G10: 230 | H10: PENDIENTE
B11: JORNADA 2 | C11: SUB 11 | D11: TLAPACOYA | E11: GUERREROS AZUL | F11: 45380 | G11: 230 | H11: PENDIENTE
B12: JORNADA 3 | C12: PONY | D12: CAR | E12: PUMAS JR | F12: 45387 | G12: 250 | H12: PENDIENTE
B13: JORNADA 3 | C13: SUB 9 | D13: CAR | E13: PACHUCA RG | F13: 45387 | G13: 250 | H13: PENDIENTE
B14: JORNADA 3 | C14: SUB 11 | D14: CAR | E14: PACHUCA RG | F14: 45387 | G14: 250 | H14: PENDIENTE
B15: JORNADA 4 | C15: PONY | D15: ALFREDO DEL MAZO | E15: MACROSOCCER | F15: 45394 | G15: 250 | H15: PENDIENTE
B16: JORNADA 4 | C16: SUB 9 | D16: CAR | E16: ATLANTE | F16: 45394 | G16: 250 | H16: PENDIENTE
B17: JORNADA 4 | C17: SUB 11 | D17: CAR | E17: SANTOS VV | F17: 45394 | G17: 250 | H17: PENDIENTE
G34: =SUM(G3:G33) -> 3570

Sheet ASISTENCIA
D2: ABRIL
D3: SEMANA 1 | G3: SEMANA 2 | J3: SEMANA 3 | M3: SEMANA 4
B4: NO. | C4: NOMBRE | D4: MAR | E4: VIE | F4: SÁB | G4: MAR | H4: VIE | I4: SÁB | J4: MAR | K4: VIE | L4: SÁB | M4: MAR | N4: VIE | O4: SÁB
D5: 1 | E5: 4 | F5: 5 | G5: 8 | H5: 11 | I5: 12 | J5: 15 | K5: 18 | L5: 19 | M5: 22 | N5: 25 | O5: 26
D6: ENTRENO | E6: ENTRENO | F6: J3 | G6: ENTRENO | H6: ENTRENO | I6: J4 | J6: ENTRENO | K6: ENTRENO | M6: ENTRENO | N6: ENTRENO
D7: TA | E7: CAR | F7: CAR | G7: TA | H7: CAR | I7: A* | J7: TA | K7: CAR | M7: TA | N7: CAR
B8: 1 | C8: Alejandro | D8: 1 | E8: 1 | F8: 1 | G8: 1 | H8: 1 | I8: 1 | J8: 0 | K8: 0 | L8: 0 | M8: 0 | N8: 0 | O8: 0
B9: 2 | C9: Aramiz | D9: 1 | E9: 1 | F9: 0 | G9: 1 | H9: 1 | I9: 0 | J9: 0 | K9: 0 | L9: 0 | M9: 0 | N9: 0 | O9: 0
B10: 3 | C10: Briand | D10: 0 | E10: 0 | F10: 0 | G10: 0 | H10: 0 | I10: 0 | J10: 0 | K10: 0 | L10: 0 | M10: 0 | N10: 0 | O10: 0
B11: 4 | C11: Carlos | D11: 1 | E11: 1 | F11: 1 | G11: 1 | H11: 1 | I11: 1 | J11: 0 | K11: 0 | L11: 0 | M11: 0 | N11: 0 | O11: 0
B12: 5 | C12: Cristopher | D12: 1 | E12: 1 | F12: 1 | G12: 1 | H12: 1 | I12: 1 | J12: 0 | K12: 0 | L12: 0 | M12: 0 | N12: 0 | O12: 0
B13: 6 | C13: Derek | D13: 1 | E13: 1 | F13: 1 | G13: 1 | H13: 1 | I13: 1 | J13: 0 | K13: 0 | L13: 0 | M13: 0 | N13: 0 | O13: 0
B14: 7 | C14: Diego | D14: 1 | E14: 0 | F14: 1 | G14: 1 | H14: 1 | I14: 1 | J14: 0 | K14: 0 | L14: 0 | M14: 0 | N14: 0 | O14: 0
B15: 8 | C15: Emiliano | D15: 1 | E15: 1 | F15: 1 | G15: 1 | H15: 1 | I15: 1 | J15: 0 | K15: 0 | L15: 0 | M15: 0 | N15: 0 | O15: 0
B16: 9 | C16: Emmanuel | D16: 1 | E16: 1 | F16: 1 | G16: 1 | H16: 1 | I16: 0 | J16: 0 | K16: 0 | L16: 0 | M16: 0 | N16: 0 | O16: 0
B17: 10 | C17: Esteban | D17: 0 | E17: 0 | F17: 0 | G17: 0 | H17: 1 | I17: 0 | J17: 0 | K17: 0 | L17: 0 | M17: 0 | N17: 0 | O17: 0
B18: 11 | C18: Franco | D18: 1 | E18: 1 | F18: 1 | G18: 1 | H18: 1 | I18: 1 | J18: 0 | K18: 0 | L18: 0 | M18: 0 | N18: 0 | O18: 0
B19: 12 | C19: Jafet | D19: 0 | E19: 1 | F19: 1 | G19: 1 | H19: 0 | I19: 0 | J19: 0 | K19: 0 | L19: 0 | M19: 0 | N19: 0 | O19: 0
... B26: 20 | C26: Mati | D26: 1 | E26: 1 | F26: 1 | G26: 1 | H26: 1 | I26: 1 | J26: 0 | K26: 0 | L26: 0 | M26: 0 | N26: 0 | O26: 0
B27: 21 | C27: Matías Mejía | D27: NA | E27: NA | F27: NA | G27: 1 | H27: 1 | I27: 1 | J27: 0 | K27: 0 | L27: 0 | M27: 0 | N27: 0 | O27: 0
B28: 22 | C28: Nico | D28: 1 | E28: 1 | F28: 1 | G28: 1 | H28: 1 | I28: 1 | J28: 0 | K28: 0 | L28: 0 | M28: 0 | N28: 0 | O28: 0
B29: 23 | C29: Ricardo | D29: 0 | E29: 0 | F29: 0 | G29: 0 | H29: 0 | I29: 0 | J29: 0 | K29: 0 | L29: 0 | M29: 0 | N29: 0 | O29: 0
B30: 24 | C30: Rodrigo | D30: 0 | E30: 1 | F30: 1 | G30: 0 | H30: 1 | I30: 1 | J30: 0 | K30: 0 | L30: 0 | M30: 0 | N30: 0 | O30: 0
B31: 25 | C31: Santiago Morales | D31: 1 | E31: 1 | F31: 1 | G31: 1 | H31: 1 | I31: 1 | J31: 0 | K31: 0 | L31: 0 | M31: 0 | N31: 0 | O31: 0
B32: 26 | C32: Santiago Uriel | D32: 1 | E32: 0 | F32: 1 | G32: 1 | H32: 0 | I32: 0 | J32: 0 | K32: 0 | L32: 0 | M32: 0 | N32: 0 | O32: 0
B33: 27 | C33: Santiago Tinajero | D33: 1 | E33: 0 | F33: 1 | G33: 1 | H33: 1 | I33: 1 | J33: 0 | K33: 0 | L33: 0 | M33: 0 | N33: 0 | O33: 0
B34: 28 | C34: Tadeo | D34: 1 | E34: 1 | F34: 1 | G34: 1 | H34: 1 | I34: 1 | J34: 0 | K34: 0 | L34: 0 | M34: 0 | N34: 0 | O34: 0
B35: 29 | C35: Valeria | D35: 1 | E35: 0 | F35: 1 | G35: 1 | H35: 0 | I35: 0 | J35: 0 | K35: 0 | L35: 0 | M35: 0 | N35: 0 | O35: 0
B36: 30 | C36: Yael | D36: 1 | E36: 1 | F36: 1 | G36: 1 | H36: 1 | I36: 1 | J36: 0 | K36: 0 | L36: 0 | M36: 0 | N36: 0 | O36: 0
B37: 31 | C37: Ximena | D37: 0 | E37: 1 | F37: 1 | G37: 1 | H37: 1 | I37: 1 | J37: 0 | K37: 0 | L37: 0 | M37: 0 | N37: 0 | O37: 0
D38: =SUM(D8:D37) -> 21 | E38: =SUM(E8:E37) -> 21 | F38: =SUM(F8:F37) -> 23 | G38: =SUM(G8:G37) -> 23 | H38: =SUM(H8:H37) -> 23 | I38: =SUM(I8:I37) -> 19 | J38: =SUM(J8:J37) -> 0 | K38: =SUM(K8:K37) -> 0 | ... O38: =SUM(O8:O37) -> 0
B40: NO ASISTIÓ POR ENFERMEDAD/LESIÓN
B41: NO ASISTIÓ, PERO AVISÓ
B42: ENTRENAMIENTO DE PRUEBA

Sheet OTROS PAGOS
D2: ABRIL
B3: NO. | C3: NOMBRE | D3: UNIFORMES | F3: INSCRIPCIÓN
B4: 1 | C4: Alejandro | D4: 0 | E4: 0 | F4: 0 | G4: 0
B5: 2 | C5: Aramiz | D5: 0 | E5: 0 | F5: 0 | G5: 0
B6: 3 | C6: Briand | D6: 0 | E6: 0 | F6: 0 | G6: 0
B7: 4 | C7: Carlos | D7: 0 | E7: 0 | F7: 500 | G7: 45751
B8: 5 | C8: Cristopher | D8: 0 | E8: 0 | F8: 0 | G8: 0
B9: 6 | C9: Derek | D9: 0 | E9: 0 | F9: 500 | G9: 45751
B10: 7 | C10: Diego | D10: 0 | E10: 0 | F10: 0 | G10: 0
B11: 8 | C11: Emiliano | D11: 0 | E11: 0 | F11: 0 | G11: 0
B12: 9 | C12: Emmanuel | D12: 0 | E12: 0 | F12: 500 | G12: 45751
B13: 10 | C13: Esteban | D13: 0 | E13: 0 | F13: 0 | G13: 0
B14: 11 | C14: Franco | D14: 0 | E14: 0 | F14: 0 | G14: 0
B15: 12 | C15: Jafet | D15: 0 | E15: 0 | F15: 1000 | G15: 45751
... B33: 31 | C33: Ximena | D33: 0 | E33: 0 | F33: 0 | G33: 0
D34: =SUM(D4:D33) -> 3400 | F34: =SUM(F4:F33) -> 7300
C35: TOTAL | D35: =D34+F34 -> 10700
C37: Pagos de inscripción a la Liga
C38: 45751 | D38: 1000
C42: TOTAL | D42: =SUM(D38:D41) -> 1000

Sheet DESCUENTO HERMANOS
C2: INSCRIPCIÓN | D2: UNIFORMES | E2: COLEGIATURA SEMANAL | F2: ARBITRAJE SEMANAL
C3: 1600 | D3: 3000 | E3: 130 | F3: 140
C5: Los montos indicados son por los dos hijos.
C6: Colegiatura y arbitraje se cubren asistan o no, a excepción de causa mayor o temas de salud.

Sheet INFO EXPEDIENTE
A1: ID | B1: Hora de inicio | C1: Hora de finalización | D1: Correo electrónico | E1: Nombre | F1: Hora de la última modificación | G1: Nombre completo: | H1: Fecha de nacimiento: | I1: Lugar de nacimiento: | J1: Lugar de residencia (colonia): | K1: Grado escolar: | L1: Talla (cm): | M1: Peso (kg): | N1: ¿Realiza otra actividad deportiva diferente al fútbol? En dado casi que sí, ¿cuál? | O1: ¿Presenta algún problema óseo o muscular, o algún trastorno/padecimiento diagnosticado? En dado casi que sí, ¿cuál? | P1: ¿Cuenta con seguro médico? | Q1: Nombre completo de la madre | R1: Fecha de nacimiento de la madre: | S1: Nombre completo del padre: | T1: Fecha de nacimiento del padre: | U1: Número telefónicos de contacto: | V1: ¿Cuál es el motivo por el que desea que su hij@ realice la actividad física? | W1: ¿Le gustaría que su hij@ sea profesional del Fútbol? ¿Por qué? | X1: Nombre a las personas y el parentesco con su hijo, de quienes podrían recogerl@ de entrenamientos y juegos: | Y1: ¿Qué esperan de nosotros como Escuela de Fútbol?
A2: 1 | B2: 10/15/24 13:46:05 | C2: 10/15/24 14:04:22 | D2: anonymous | G2: Ximena grijalva reyes | H2: 2/26/2016 | I2: Ciudad de mexico | J2: citlamina | K2: 3 primaria | L2: 10 | M2: 24 | N2: no ninguna | O2: no | P2: Sí | Q2: Norma lizbeth Reyes ibarra | R2: 32449 | S2: Heriberto grijalva reyes | T2: 31139 | U2: 5559465611 | V2: a ella le gusta mucho | W2: No lo se aun | X2: Yaquelin reyes tía | Y2: una buena formación para los niños
A3: 2 | B3: 10/15/24 13:55:38 | C3: 10/15/24 14:08:26 | D3: anonymous | G3: Derek David Hernández Gaytan | H3: 1/20/2017 | I3: México | J3: San Buenaventura | K3: 2° de primaria | L3: 1.33 | M3: 28300 | N3: No | O3: TDAH e impulsividad | P3: Sí | Q3: Claudian Arianna Gaytan León | R3: 5/14/1987 | S3: David Manzur Hernández Peña | T3: 11/23/1992 | U3: 5536672637 | V3: Es bueno para la salud y por su trastorno a el le ayuda mucho a disciplina y sacar energía | W3: Si a el le gusta y es su sueño claro q si lo apoyaría | X3: Fidel Angel Gaytan Lopez (Abuelo) Juana Edith León Lopez (Abuela) | Y3: Que mi hijo se supere cada día aprendiendo más cosas, q se divierta jugando, convivencia sana y respeto
A4: 3 | B4: 10/15/24 13:58:50 | C4: 10/15/24 14:10:00 | D4: anonymous | G4: Jose Alberto Delfino Delgado | H4: 7/27/2013 | I4: Cdmx | J4: Heroes Ixtapaluca | K4: 6to | L4: 1.49 | M4: 47 | N4: No | O4: Ninguno | P4: Sí | Q4: Ana Delgado Bibiano | R4: 2/15/1984 | S4: Alberto Delfino Hernández | T4: 29437 | U4: 5512468470 | V4: Quiero que forme una buena disciplina,que sepa trabajar en equipo,que sea comprometido | W4: Si me gustaría por qué se que lo hace feliz se que le gusta y disfruta jugar fútbol ⚽ | X4: Ana Delgado Bibiano Alberto Delfino Hernández Isaac Francisco Delfino | Y4: Que sean profesionales,que tengan siempre la mejor propuesta para que el equipo salga adelante y siga creciendo sea un equipo fuerte y reconocido
A5: 4 | B5: 10/17/24 12:53:28 | C5: 10/17/24 13:05:47 | D5: anonymous | G5: SANTIAGO MORALES HERNÁNDEZ | H5: 6/26/2015 | I5: Ciudad de Mexico | J5: Centro Ixtapaluca | K5: 4 de primaria | L5: 1.33 | M5: 34 kilos | N5: No | O5: No | P5: No | Q5: María Guadalupe Hernández Pozos | R5: 7/24/1988 | S5: Jaime Morales Palafox | T5: 11/22/1987 | U5: 5517987922 | V5: Salud física y mental | W5: Le gusta mucho el futbol, lo apoyo hasta donde él quiera llegar | X5: Abuelo Gregorio Hernández Abuela Lina Pozos | Y5: Un equipo, profesionalismo y alguien con quien mi hijo se sienta seguro
A6: 5 | B6: 10/17/24 19:28:20 | C6: 10/17/24 20:23:42 | D6: anonymous | G6: Tadeo Darío Pantoja Vieyra | H6: 41955 | I6: Ciudad de México | J6: Las Palmas tres | K6: 5° Grado de Primaria | L6: 1.38 cm | M6: 21,800 kg | N6: Ninguna | O6: Alergia a los ácaros | P6: Sí | Q6: Claudia Vieyra Medrano | R6: 28374 | S6: Roberto Pantoja García | T6: 28009 | U6: 5580499218 (papá) 5573635300 (mamá) | V6: Para su óptimo desarrollo, físico, mental y emocional | W6: Si nos gustaría, porque es algo que él desea, le emociona y le gustaría mucho, sabemos que es un camino difícil más no imposible, y creemos vamos por buen comienzo. | X6: Papá, Mamá, Hermano Leonardo Pantoja Vieyra, y algunas veces nos apoyamos con los papás de Rodrigo | Y6: Que sienten las bases en cuanto conocimientos en el fútbol, disciplina, desarrollo de habilidades, destrezas que el deporte exige, si me gustaría que no sólo un rato de actividad física, que sea realmente una escuela con disciplina, órden, que se les exija a los niños dar lo mejor de sí, que se les vea una evolución, todo ello en un ambiente de respeto, compañerismo y sana convivencia con todos los que estamos alrededor de los niños (equipo, papás, profesores ) así mismo nos comprometemos a dar lo que a nosotros nos confiere, también me gustaría que en alguna ocasión nos den una retroalimentación en particular de mi hijo como va, si avanza o no, tal vez que se le puede reforzar, si lo ven con aptitudes de llegar lejos o no. Y Gracias por haber tomado el reto Profes es el inicio de algo Grande 😊
A7: 6 | B7: 10/17/24 20:30:55 | C7: 10/17/24 20:41:31 | D7: anonymous | G7: IRVING EMILIANO SOLORZANO RANGEL | H7: 41467 | I7: CHALCO | J7: JORGE JIMENEZ CANTU | K7: 6° | L7: 155 | M7: 53 | N7: FUTBOL EN EL TORNEO DE LA ESCUELA | O7: NO | P7: No | Q7: XITLALIC ITZEL RANGEL FARIAS | R7: 33941 | S7: JUAN JOSE RANGEL ORTEGA | T7: 24169 | U7: 5530536185 | V7: LE GUSTA EL FUTBOL Y ESTE SANO | W7: SI EL LO DESEA, SI; PORQUE ES SU SUEÑO Y PORQUE LE GUSTA | X7: XITLALIC ITZEL RANGEL FARIAS XITLALIC FARIAS MUÑOZ JUAN JOSE RANGEL ORTEGA | Y7: QUE FORMEN A MI HIJO DE FORMA INTEGRAL, QUE ENSEÑEN AL TRABAJO EN EQUIPO Y QUE ENTUSIASMEN A LOS CHICOS, YA QUE ESO LOS MOTIVA
A8: 7 | B8: 10/17/24 20:42:56 | C8: 10/17/24 21:04:42 | D8: anonymous | G8: Rodrigo Ulises Ortega Carrillo | H8: 11/29/2013 | I8: Ciudad de México | J8: Palmas III | K8: 6to primaria | L8: 1.35 | M8: 27 | N8: Ninguna | O8: Ninguno | P8: Sí | Q8: Karla R. Carrillo Gómez | R8: 28618 | S8: Gabriel Ortega Alarcón | T8: 8/24/1974 | U8: 5513669946 - 5550699176 | V8: Por gusto del pequeño | W8: Si, es su sueño | X8: Gabriel Ortega y Karla Carrillo | Y8: Que el pequeño crezca futbolísticamente y que se busquen oportunidades para cumplir su sueño, impulsarlo en alguna oportunidad que se pueda presentar
A9: 8 | B9: 10/17/24 21:27:36 | C9: 10/17/24 21:35:12 | D9: anonymous | G9: Liam Mateo García Gomez | H9: 42529 | I9: Ciudad de México | J9: San Buenaventura | K9: 3 primaria | L9: 10 | M9: 20kg | N9: No | O9: No | P9: Sí | Q9: Sheila Gabriela Gómez Cortes | R9: 34029 | S9: Erick García Solchaga | T9: 9/27/1993 | U9: 5611923898 / 5618702925 | V9: Salud física, mental, compromiso, responsabilidad, compañerismo | W9: Si es el sueño de Liam será por decisión de él y contará con nuestro apoyo | X9: Juan García - abuelo Diana Solchaga - abuela Cristina Cortes - abuela Gabriel Gómez - abuelo | Y9: Formación física, personal así como inculcar valores que aporten su crecimiento.
A10: 9 | B10: 10/17/24 21:55:43 | C10: 10/17/24 22:00:11 | D10: anonymous | G10: Cristopher Antonio Maldonado López | H10: 5/20/2013 | I10: Cdmx | J10: San buenaventura | K10: 6 | L10: 1.25 | M10: 44 | N10: No | O10: No | P10: No | Q10: Gabriela Ivette López Castelan | R10: 5/25/1995 | S10: José Antonio Maldonado mejia | T10: 4/23/1992 | U10: 5619320744 | V10: Le encanta el partido y quiere superarse | W10: Si | X10: Ariana Gaytán | Y10: Ser una escuela super exitosa q logren el sábado xito junto con sus niños
A11: 10 | B11: 10/18/24 9:31:54 | C11: 10/18/24 9:42:01 | D11: anonymous | G11: Calderón Beltrán Emmanuel | H11: 5/21/2013 | I11: San Buenaventura, Ixtapaluca Estado de México | J11: Ampliación San Francisco | K11: Sexto de primaria | L11: 142 | M11: 42 | N11: No | O11: No | P11: No | Q11: Beltrán García Evelin | R11: 2/15/1993 | S11: Calderón Hine Oscar Daniel | T11: 1/27/1993 | U11: 5518329647 | V11: Para que tenga un buen desarrollo físico, mental ,motriz y también porque es algo le ayuda en el ámbito social y como individuo para que despeje la mente de las actividades del día a día. | W11: Si es un sueño para él, nosotros como padres estamos en la mejor disposición de apoyarlo , por qué a final de cuenta no es lo que nosotros queramos , es lo que a él le guste y se sienta cómodo con ellos | X11: Oscar Daniel Calderón Hine (padre) Evelin Beltrán García (madre) Erick Beltrán García (tío) | Y11: Que comprometidos y honestos , buen trato hacia los alumnos. Que sean capaces de impartir disciplina en un ambiente seguro ,cómodo y amigable.
A12: 11 | B12: 10/18/24 14:55:06 | C12: 10/18/24 15:19:14 | D12: anonymous | G12: Leonel Alejandro Méndez Ruiz | H12: 4/13/2016 | I12: Estado de México | J12: Santa barbara Ixtapaluca | K12: Segundo grado | L12: 1.30 | M12: 30 k | N12: No | O12: Ninguno | P12: Sí | Q12: Nancy Ruiz calderón | R12: 7/23/1981 | S12: Lino Méndez laso | T12: 28460 | U12: 5564529149 | V12: Por salud | W12: Sí | X12: Nancy Ruiz calderón. Mamá Lino Méndez laso. Papá | Y12: Disciplina
A13: 12 | B13: 10/25/24 15:44:05 | C13: 10/25/24 15:51:43 | D13: anonymous | G13: Briand Said Hernandez Torres | H13: 5/29/2013 | I13: Ixtapaluca Estado de mexico | J13: El tablon | K13: 6 to de primaria | L13: 147 | M13: 40 | N13: No | O13: No | P13: No | Q13: Evelyn Torres Hernandez | R13: 6/14/1995 | S13: Irving Brian Hernandez Ramirez | T13: 3/14/1995 | U13: 5572452737 | V13: Por gusto | W13: Si Por que es su sueño más grande | X13: Evelyn Torres Hernandez (MADRE) Irving Hernandez Ramirez (PADRE) | Y13: Que le enseñen mucha disciplina y compromiso
A14: 13 | B14: 10/31/24 8:59:41 | C14: 10/31/24 9:06:15 | D14: anonymous | G14: MATIAS ALEJANDRO SILVA BAUTISTA | H14: 42347 | I14: ECATEPEC, ESTADO DE MÉXICO | J14: LOS HÉROES, IXTAPALUCA | K14: 4TO | L14: 1.30 | M14: 33 | N14: NO | O14: SÍ, ASMA. | P14: Sí | Q14: NAYELI IRAIS BAUTISTA GARCÍA | R14: 33699 | S14: JUAN LUIS SILVA AVILA | T14: 6/18/1986 | U14: 5540625282 - 5579005387 | V14: ADQUIERA VALORES, COMPROMISO Y DISCIPLINA. | W14: NOTO QUE A ÉL LE GUSTA Y PIENSA EN ELLO, SI ESO ES LO QUE QUIERE, LO APOYAREMOS MUCHO. | X14: NAYELI IRAIS BAUTISTA GARCÍA (MADRE), JORGE SANTOS (ABUELITO), ROSA GARCÍA (ABUELITA). | Y14: QUE MI HIJO ESTÉ CONTENTO Y DISFRUTE MUCHO LO QUE HAGA.
A15: 14 | B15: 45302.471 | C15: 45302.477 | D15: anonymous | G15: Lionel Palmerin Mora | H15: 3/28/2015 | I15: Ixtapaluca | J15: Tlayehuale | K15: 4 primaria | L15: 145 cm | M15: 50 | N15: Natación | O15: No | P15: No | Q15: Karen Mora cruz | R15: 7/26/1988 | S15: Juan Carlos Palmerin Fonseca | T15: 1/24/1978 | U15: 5543773246 | V15: Le gusta mucho el futbol | W15: No | X15: Karen Mora cruz Juan Carlos Palmerin Fonseca | Y15: Que mi hijo se divierta ,aprenda a jugar bien el fútbol
A16: 15 | B16: 11/21/24 11:49:17 | C16: 11/21/24 12:01:55 | D16: anonymous | G16: Franco Ruiz Ponce | H16: 6/22/2018 | I16: Estado de México | J16: La venta Ixtapaluca | K16: Primero de primaria | L16: 1.26 | M16: 26 | N16: Ninguna | O16: No | P16: Sí | Q16: Laura Ponce Benitez | R16: 33519 | S16: Ulises Ruiz Pozos | T16: 31757 | U16: 5544713968 | V16: Para un mejor rendimiento y disciplina | W16: No, xq solo es por distracción | X16: Laura Ponce Benitez madre Ulises Ruiz Pozos padre | Y16: Que tenga un buen desarrollo en lo físico familia me y social
A17: 16 | B17: 45394.892 | C17: 45394.899 | D17: anonymous | G17: Jafet Itzae Reyes Ibarra | H17: 4/15/2015 | I17: Ciudad de Mexico | J17: Col.Valle Verde Ixtapaluca | K17: 4° | L17: 1.40 cm | M17: 26 kg | N17: Ninguna | O17: Ninguno | P17: Sí | Q17: Abril Gabriela Ibarra Trejo | R17: 1/30/1981 | S17: Isaac reyes Rodríguez | T17: 27764 | U17: 5513582517 | V17: Por salud | W17: No busco que sea profesional, me gusta que realice deporte | X17: Hilda Trejo Guzmán (abuela) Alvaro Ibarra Sánchez (abuelo) | Y17: Fomentar las habilidades del fútbol, las acciones técnicas y tácticas, más conocimiento del deporte, valores.
A18: 17 | B18: 45638.715 | C18: 45638.723 | D18: anonymous | G18: Ricardo Jaziel Leon Díaz | H18: 1/25/2014 | I18: Estado de México | J18: San Buenaventura | K18: Quinto | L18: 14 | M18: 40 | N18: No | O18: No | P18: Sí | Q18: Jarmín Díaz Enciso | R18: 29714 | S18: Ricardo Leon Martell | T18: 12/13/2024 | U18: 5561935871 | V18: Desarrollo físico y mental | W18: Si | X18: Cristian Jarek Miranda Díaz | Y18: Que tenga un crecimiento deportivo
A19: 18 | B19: 12/16/24 11:23:31 | C19: 12/16/24 11:29:02 | D19: anonymous | G19: Esteban Pantoja Caballero | H19: 42097 | I19: CDMX | J19: Ampliación Acozac | K19: 4o primaria | L19: 1.34 cm | M19: 33kg | N19: Béisbol | O19: Ninguno | P19: Sí | Q19: Bertha Caballero Baz | R19: 31382 | S19: Rodrigo Pantoja Gutiérrez | T19: 5/25/1981 | U19: 5540904600 5539939326 | V19: Es importante practicar un deporte o actividad extra | W19: El quiere ser profesional y nosotros lo apoyamos | X19: Guadalupe Baz Zaballa abuela materna | Y19: Entrenamientos completos e inculcar valores
A20: 19 | B20: 1/23/25 12:58:32 | C20: 1/23/25 13:03:20 | D20: anonymous | G20: Yael Daniel Ubaldo Martinez | H20: 7/18/2015 | I20: Estado de mexico | J20: San buenaventura Ixtapaluca | K20: 4 | L20: 144 | M20: 37kg | N20: No ninguna | O20: No | P20: No | Q20: Nallely Fernanda Martinez Chávez | R20: 11/26/1991 | S20: Yosmar Fabián Arzate flores | T20: 3/28/1998 | U20: 7294772804 | V20: Por qué le gusta el futbol | W20: Si porque es su sueño | X20: Yosmar FABIAN | Y20: Enseñanza y aprendizaje
